qwertzsite/__init__.py
qwertzsite/app.py
qwertzsite/body.py
qwertzsite/button.py
qwertzsite/css.py
qwertzsite/elements.py
qwertzsite/image.py
qwertzsite/newline.py
qwertzsite/page.py
qwertzsite/server.py
qwertzsite/text.py
qwertzsite/title.py
qwertzsite_QWERTZ-0.1.dist-info/LICENSE
qwertzsite_QWERTZ-0.1.dist-info/METADATA
qwertzsite_QWERTZ-0.1.dist-info/WHEEL
qwertzsite_QWERTZ-0.1.dist-info/top_level.txt
qwertzsite_QWERTZ-0.1.dist-info/RECORD
