Metadata-Version: 2.1
Name: qwertzsite-QWERTZ
Version: 0.1
Summary: A framework for easily creating and serving websites
Author: QWERTZ_EXE
License: AGPL v3
License-File: LICENSE
